loginit
