Metadata-Version: 1.0
Name: LogInit
Version: 1.2.6
Summary: The logging init model
Home-page: https://git.oschina.net/myPyLib/log-Init
Author: Jiangxumin
Author-email: jxm_zn@163.com
License: MIT
Platform: any
